.coveragerc
.editorconfig
.gitignore
.travis.yml
LICENSE
README.md
democritus_strings_docs.json
pyproject.toml
requirements.txt
requirements_dev.txt
setup.cfg
setup.py
.github/workflows/python-publish.yml
democritus_strings/__init__.py
democritus_strings/strings.py
democritus_strings/strings_temp_utils.py
democritus_strings.egg-info/PKG-INFO
democritus_strings.egg-info/SOURCES.txt
democritus_strings.egg-info/dependency_links.txt
democritus_strings.egg-info/requires.txt
democritus_strings.egg-info/top_level.txt
democritus_strings.egg-info/zip-safe
tests/__init__.py
tests/test_strings.py